bmkg/__init__.py
bmkgnasir-0.3.2.dist-info/LICENSE
bmkgnasir-0.3.2.dist-info/METADATA
bmkgnasir-0.3.2.dist-info/WHEEL
bmkgnasir-0.3.2.dist-info/top_level.txt
bmkgnasir-0.3.2.dist-info/RECORD
