Metadata-Version: 2.1
Name: bmkgnasir
Version: 0.3.2
Summary: retrieve latest earthquake information in Indonesia
Home-page: https://github.com/nasirnooruddin/latest-indonesia-earthquake
Author: Nasir Nooruddin
Author-email: nasir@nasir.id
License: UNKNOWN
Project-URL: Website, http://nasir.id
Platform: UNKNOWN
Classifier: Programming Language :: Python :: 3
Classifier: License :: OSI Approved :: MIT License
Classifier: Operating System :: OS Independent
Requires-Python: >=3.6
License-File: LICENSE
